setup.py
foursquare/__init__.py
foursquare/source_code_analysis/__init__.py
foursquare/source_code_analysis/exception.py
foursquare/source_code_analysis/rewrite_cursor.py
foursquare/source_code_analysis/source_file_rewriter.py
foursquare/source_code_analysis/source_file_scanner.py
foursquare/source_code_analysis/scala/__init__.py
foursquare/source_code_analysis/scala/scala_import_parser.py
foursquare/source_code_analysis/scala/scala_import_rewriter.py
foursquare/source_code_analysis/scala/scala_import_sorter.py
foursquare/source_code_analysis/scala/scala_imports.py
foursquare/source_code_analysis/scala/scala_source_file_rewriter.py
foursquare/source_code_analysis/scala/scala_unused_import_remover.py
foursquare/source_code_analysis/scala/scripts/__init__.py
foursquare/source_code_analysis/scala/scripts/scala_import_sorter.py
foursquare/source_code_analysis/scala/scripts/scala_unused_import_remover.py
scala_source_tools.egg-info/PKG-INFO
scala_source_tools.egg-info/SOURCES.txt
scala_source_tools.egg-info/dependency_links.txt
scala_source_tools.egg-info/entry_points.txt
scala_source_tools.egg-info/top_level.txt
scripts/git-fix-scala-imports.sh