Metadata-Version: 1.0
Name: scala-source-tools
Version: 0.13
Summary: Scala source analysis tools from foursquare
Home-page: https://www.python.org/sigs/distutils-sig/
Author: Benjy W
Author-email: benjy@foursquare.com
License: UNKNOWN
Platform: UNKNOWN
